square/__init__.py
square/__main__.py
seismopy-1.0.1.dist-info/METADATA
seismopy-1.0.1.dist-info/WHEEL
seismopy-1.0.1.dist-info/top_level.txt
seismopy-1.0.1.dist-info/RECORD
